{"data":[{"ProvID":5,"Provinsi":"Kepulauan Riau","Tanggal":"29 Apr 26","Komoditas":"Bawang Merah","Nilai":29850.00,"NilaiDiff":"Rp0","SemuaProvinsi":46050.00,"Kelompok":5,"stdDev":8400.00,"Percentage":0.00,"SemuaPercentage":0.00,"stdDevPercentage":null,"TanggalLast":"28 Apr 26","TanggalInflasi":"29 Apr / 28 Apr","show":true},{"ProvID":17,"Provinsi":"Bali","Tanggal":"29 Apr 26","Komoditas":"Bawang Merah","Nilai":36750.00,"NilaiDiff":"-Rp300","SemuaProvinsi":46050.00,"Kelompok":5,"stdDev":8400.00,"Percentage":-0.81,"SemuaPercentage":0.00,"stdDevPercentage":null,"TanggalLast":"28 Apr 26","TanggalInflasi":"29 Apr / 28 Apr","show":true},{"ProvID":1,"Provinsi":"Aceh","Tanggal":"29 Apr 26","Komoditas":"Bawang Merah","Nilai":37600.00,"NilaiDiff":"-Rp250","SemuaProvinsi":46050.00,"Kelompok":5,"stdDev":8400.00,"Percentage":-0.66,"SemuaPercentage":0.00,"stdDevPercentage":null,"TanggalLast":"28 Apr 26","TanggalInflasi":"29 Apr / 28 Apr","show":true},{"ProvID":6,"Provinsi":"Jambi","Tanggal":"29 Apr 26","Komoditas":"Bawang Merah","Nilai":37650.00,"NilaiDiff":"-Rp750","SemuaProvinsi":46050.00,"Kelompok":5,"stdDev":8400.00,"Percentage":-1.95,"SemuaPercentage":0.00,"stdDevPercentage":null,"TanggalLast":"28 Apr 26","TanggalInflasi":"29 Apr / 28 Apr","show":true},{"ProvID":2,"Provinsi":"Sumatera Utara","Tanggal":"29 Apr 26","Komoditas":"Bawang Merah","Nilai":39000.00,"NilaiDiff":"Rp0","SemuaProvinsi":46050.00,"Kelompok":4,"stdDev":8400.00,"Percentage":0.00,"SemuaPercentage":0.00,"stdDevPercentage":null,"TanggalLast":"28 Apr 26","TanggalInflasi":"29 Apr / 28 Apr","show":true},{"ProvID":3,"Provinsi":"Sumatera Barat","Tanggal":"29 Apr 26","Komoditas":"Bawang Merah","Nilai":39250.00,"NilaiDiff":"Rp500","SemuaProvinsi":46050.00,"Kelompok":4,"stdDev":8400.00,"Percentage":1.29,"SemuaPercentage":0.00,"stdDevPercentage":null,"TanggalLast":"28 Apr 26","TanggalInflasi":"29 Apr / 28 Apr","show":true},{"ProvID":26,"Provinsi":"Sulawesi Selatan","Tanggal":"29 Apr 26","Komoditas":"Bawang Merah","Nilai":39500.00,"NilaiDiff":"Rp0","SemuaProvinsi":46050.00,"Kelompok":4,"stdDev":8400.00,"Percentage":0.00,"SemuaPercentage":0.00,"stdDevPercentage":null,"TanggalLast":"28 Apr 26","TanggalInflasi":"29 Apr / 28 Apr","show":true},{"ProvID":18,"Provinsi":"Nusa Tenggara Barat","Tanggal":"29 Apr 26","Komoditas":"Bawang Merah","Nilai":39650.00,"NilaiDiff":"Rp1650","SemuaProvinsi":46050.00,"Kelompok":4,"stdDev":8400.00,"Percentage":4.34,"SemuaPercentage":0.00,"stdDevPercentage":null,"TanggalLast":"28 Apr 26","TanggalInflasi":"29 Apr / 28 Apr","show":true},{"ProvID":4,"Provinsi":"Riau","Tanggal":"29 Apr 26","Komoditas":"Bawang Merah","Nilai":40050.00,"NilaiDiff":"Rp0","SemuaProvinsi":46050.00,"Kelompok":4,"stdDev":8400.00,"Percentage":0.00,"SemuaPercentage":0.00,"stdDevPercentage":null,"TanggalLast":"28 Apr 26","TanggalInflasi":"29 Apr / 28 Apr","show":true},{"ProvID":16,"Provinsi":"Jawa Timur","Tanggal":"29 Apr 26","Komoditas":"Bawang Merah","Nilai":40650.00,"NilaiDiff":"Rp250","SemuaProvinsi":46050.00,"Kelompok":4,"stdDev":8400.00,"Percentage":0.62,"SemuaPercentage":0.00,"stdDevPercentage":null,"TanggalLast":"28 Apr 26","TanggalInflasi":"29 Apr / 28 Apr","show":true},{"ProvID":10,"Provinsi":"Lampung","Tanggal":"29 Apr 26","Komoditas":"Bawang Merah","Nilai":41150.00,"NilaiDiff":"Rp0","SemuaProvinsi":46050.00,"Kelompok":4,"stdDev":8400.00,"Percentage":0.00,"SemuaPercentage":0.00,"stdDevPercentage":null,"TanggalLast":"28 Apr 26","TanggalInflasi":"29 Apr / 28 Apr","show":true},{"ProvID":8,"Provinsi":"Sumatera Selatan","Tanggal":"29 Apr 26","Komoditas":"Bawang Merah","Nilai":41900.00,"NilaiDiff":"Rp0","SemuaProvinsi":46050.00,"Kelompok":4,"stdDev":8400.00,"Percentage":0.00,"SemuaPercentage":0.00,"stdDevPercentage":null,"TanggalLast":"28 Apr 26","TanggalInflasi":"29 Apr / 28 Apr","show":true},{"ProvID":14,"Provinsi":"Jawa Tengah","Tanggal":"29 Apr 26","Komoditas":"Bawang Merah","Nilai":42250.00,"NilaiDiff":"Rp400","SemuaProvinsi":46050.00,"Kelompok":4,"stdDev":8400.00,"Percentage":0.96,"SemuaPercentage":0.00,"stdDevPercentage":null,"TanggalLast":"28 Apr 26","TanggalInflasi":"29 Apr / 28 Apr","show":true},{"ProvID":30,"Provinsi":"Sulawesi Barat","Tanggal":"29 Apr 26","Komoditas":"Bawang Merah","Nilai":42350.00,"NilaiDiff":"Rp0","SemuaProvinsi":46050.00,"Kelompok":4,"stdDev":8400.00,"Percentage":0.00,"SemuaPercentage":0.00,"stdDevPercentage":null,"TanggalLast":"28 Apr 26","TanggalInflasi":"29 Apr / 28 Apr","show":true},{"ProvID":15,"Provinsi":"DI Yogyakarta","Tanggal":"29 Apr 26","Komoditas":"Bawang Merah","Nilai":44000.00,"NilaiDiff":"Rp0","SemuaProvinsi":46050.00,"Kelompok":4,"stdDev":8400.00,"Percentage":0.00,"SemuaPercentage":0.00,"stdDevPercentage":null,"TanggalLast":"28 Apr 26","TanggalInflasi":"29 Apr / 28 Apr","show":true},{"ProvID":21,"Provinsi":"Kalimantan Selatan","Tanggal":"29 Apr 26","Komoditas":"Bawang Merah","Nilai":44250.00,"NilaiDiff":"-Rp850","SemuaProvinsi":46050.00,"Kelompok":4,"stdDev":8400.00,"Percentage":-1.88,"SemuaPercentage":0.00,"stdDevPercentage":null,"TanggalLast":"28 Apr 26","TanggalInflasi":"29 Apr / 28 Apr","show":true},{"ProvID":28,"Provinsi":"Sulawesi Tengah","Tanggal":"29 Apr 26","Komoditas":"Bawang Merah","Nilai":45250.00,"NilaiDiff":"-Rp2500","SemuaProvinsi":46050.00,"Kelompok":4,"stdDev":8400.00,"Percentage":-5.24,"SemuaPercentage":0.00,"stdDevPercentage":null,"TanggalLast":"28 Apr 26","TanggalInflasi":"29 Apr / 28 Apr","show":true},{"ProvID":12,"Provinsi":"Jawa Barat","Tanggal":"29 Apr 26","Komoditas":"Bawang Merah","Nilai":46050.00,"NilaiDiff":"Rp950","SemuaProvinsi":46050.00,"Kelompok":4,"stdDev":8400.00,"Percentage":2.11,"SemuaPercentage":0.00,"stdDevPercentage":null,"TanggalLast":"28 Apr 26","TanggalInflasi":"29 Apr / 28 Apr","show":true},{"ProvID":22,"Provinsi":"Kalimantan Tengah","Tanggal":"29 Apr 26","Komoditas":"Bawang Merah","Nilai":46400.00,"NilaiDiff":"Rp0","SemuaProvinsi":46050.00,"Kelompok":4,"stdDev":8400.00,"Percentage":0.00,"SemuaPercentage":0.00,"stdDevPercentage":null,"TanggalLast":"28 Apr 26","TanggalInflasi":"29 Apr / 28 Apr","show":true},{"ProvID":7,"Provinsi":"Bengkulu","Tanggal":"29 Apr 26","Komoditas":"Bawang Merah","Nilai":46500.00,"NilaiDiff":"Rp250","SemuaProvinsi":46050.00,"Kelompok":4,"stdDev":8400.00,"Percentage":0.54,"SemuaPercentage":0.00,"stdDevPercentage":null,"TanggalLast":"28 Apr 26","TanggalInflasi":"29 Apr / 28 Apr","show":true},{"ProvID":19,"Provinsi":"Nusa Tenggara Timur","Tanggal":"29 Apr 26","Komoditas":"Bawang Merah","Nilai":46650.00,"NilaiDiff":"Rp0","SemuaProvinsi":46050.00,"Kelompok":4,"stdDev":8400.00,"Percentage":0.00,"SemuaPercentage":0.00,"stdDevPercentage":null,"TanggalLast":"28 Apr 26","TanggalInflasi":"29 Apr / 28 Apr","show":true},{"ProvID":29,"Provinsi":"Sulawesi Utara","Tanggal":"29 Apr 26","Komoditas":"Bawang Merah","Nilai":46650.00,"NilaiDiff":"Rp0","SemuaProvinsi":46050.00,"Kelompok":4,"stdDev":8400.00,"Percentage":0.00,"SemuaPercentage":0.00,"stdDevPercentage":null,"TanggalLast":"28 Apr 26","TanggalInflasi":"29 Apr / 28 Apr","show":true},{"ProvID":25,"Provinsi":"Gorontalo","Tanggal":"29 Apr 26","Komoditas":"Bawang Merah","Nilai":46900.00,"NilaiDiff":"Rp1250","SemuaProvinsi":46050.00,"Kelompok":4,"stdDev":8400.00,"Percentage":2.74,"SemuaPercentage":0.00,"stdDevPercentage":null,"TanggalLast":"28 Apr 26","TanggalInflasi":"29 Apr / 28 Apr","show":true},{"ProvID":13,"Provinsi":"DKI Jakarta","Tanggal":"29 Apr 26","Komoditas":"Bawang Merah","Nilai":48250.00,"NilaiDiff":"Rp0","SemuaProvinsi":46050.00,"Kelompok":3,"stdDev":8400.00,"Percentage":0.00,"SemuaPercentage":0.00,"stdDevPercentage":null,"TanggalLast":"28 Apr 26","TanggalInflasi":"29 Apr / 28 Apr","show":true},{"ProvID":23,"Provinsi":"Kalimantan Timur","Tanggal":"29 Apr 26","Komoditas":"Bawang Merah","Nilai":48350.00,"NilaiDiff":"Rp0","SemuaProvinsi":46050.00,"Kelompok":3,"stdDev":8400.00,"Percentage":0.00,"SemuaPercentage":0.00,"stdDevPercentage":null,"TanggalLast":"28 Apr 26","TanggalInflasi":"29 Apr / 28 Apr","show":true},{"ProvID":11,"Provinsi":"Banten","Tanggal":"29 Apr 26","Komoditas":"Bawang Merah","Nilai":49750.00,"NilaiDiff":"Rp350","SemuaProvinsi":46050.00,"Kelompok":3,"stdDev":8400.00,"Percentage":0.71,"SemuaPercentage":0.00,"stdDevPercentage":null,"TanggalLast":"28 Apr 26","TanggalInflasi":"29 Apr / 28 Apr","show":true},{"ProvID":9,"Provinsi":"Kepulauan Bangka Belitung","Tanggal":"29 Apr 26","Komoditas":"Bawang Merah","Nilai":51000.00,"NilaiDiff":"-Rp400","SemuaProvinsi":46050.00,"Kelompok":3,"stdDev":8400.00,"Percentage":-0.78,"SemuaPercentage":0.00,"stdDevPercentage":null,"TanggalLast":"28 Apr 26","TanggalInflasi":"29 Apr / 28 Apr","show":true},{"ProvID":24,"Provinsi":"Kalimantan Utara","Tanggal":"29 Apr 26","Komoditas":"Bawang Merah","Nilai":51250.00,"NilaiDiff":"-Rp1000","SemuaProvinsi":46050.00,"Kelompok":3,"stdDev":8400.00,"Percentage":-1.91,"SemuaPercentage":0.00,"stdDevPercentage":null,"TanggalLast":"28 Apr 26","TanggalInflasi":"29 Apr / 28 Apr","show":true},{"ProvID":27,"Provinsi":"Sulawesi Tenggara","Tanggal":"29 Apr 26","Komoditas":"Bawang Merah","Nilai":51250.00,"NilaiDiff":"Rp0","SemuaProvinsi":46050.00,"Kelompok":3,"stdDev":8400.00,"Percentage":0.00,"SemuaPercentage":0.00,"stdDevPercentage":null,"TanggalLast":"28 Apr 26","TanggalInflasi":"29 Apr / 28 Apr","show":true},{"ProvID":20,"Provinsi":"Kalimantan Barat","Tanggal":"29 Apr 26","Komoditas":"Bawang Merah","Nilai":51650.00,"NilaiDiff":"Rp550","SemuaProvinsi":46050.00,"Kelompok":3,"stdDev":8400.00,"Percentage":1.08,"SemuaPercentage":0.00,"stdDevPercentage":null,"TanggalLast":"28 Apr 26","TanggalInflasi":"29 Apr / 28 Apr","show":true},{"ProvID":31,"Provinsi":"Maluku","Tanggal":"29 Apr 26","Komoditas":"Bawang Merah","Nilai":53150.00,"NilaiDiff":"Rp0","SemuaProvinsi":46050.00,"Kelompok":3,"stdDev":8400.00,"Percentage":0.00,"SemuaPercentage":0.00,"stdDevPercentage":null,"TanggalLast":"28 Apr 26","TanggalInflasi":"29 Apr / 28 Apr","show":true},{"ProvID":34,"Provinsi":"Papua Barat","Tanggal":"29 Apr 26","Komoditas":"Bawang Merah","Nilai":57500.00,"NilaiDiff":"Rp0","SemuaProvinsi":46050.00,"Kelompok":2,"stdDev":8400.00,"Percentage":0.00,"SemuaPercentage":0.00,"stdDevPercentage":null,"TanggalLast":"28 Apr 26","TanggalInflasi":"29 Apr / 28 Apr","show":true},{"ProvID":33,"Provinsi":"Papua","Tanggal":"29 Apr 26","Komoditas":"Bawang Merah","Nilai":70000.00,"NilaiDiff":"Rp500","SemuaProvinsi":46050.00,"Kelompok":1,"stdDev":8400.00,"Percentage":0.72,"SemuaPercentage":0.00,"stdDevPercentage":null,"TanggalLast":"28 Apr 26","TanggalInflasi":"29 Apr / 28 Apr","show":true},{"ProvID":32,"Provinsi":"Maluku Utara","Tanggal":"29 Apr 26","Komoditas":"Bawang Merah","Nilai":72500.00,"NilaiDiff":"Rp0","SemuaProvinsi":46050.00,"Kelompok":1,"stdDev":8400.00,"Percentage":0.00,"SemuaPercentage":0.00,"stdDevPercentage":null,"TanggalLast":"28 Apr 26","TanggalInflasi":"29 Apr / 28 Apr","show":true}]}